[{"WATER_SYSTEM_NUMBER":"CA4900716","WATER_SYSTEM_NAME":"CINNABAR ELEMENTARY SCHOOL","CITY":"PETALUMA","COUNTY":"SONOMA","ZIPCODE":"94952","CLASSIFICATION":"NON-TRANSIENT NON-COMMUNITY","POPULATION":"350","SERVICE_CONNECTIONS":"1","REGULATING_AGENCY":"DISTRICT 18 - SONOMA","VIOLATION_NUMBER":"718003","VIOLATION_TYPE_NAME":"MCL,  AVERAGE","ANALYTE_NAME":"ARSENIC","RESULT":".0113 MG/L","MCL":"NA","VIOL_BEGIN_DATE":"2013-01-01","VIOL_END_DATE":"2013-03-31","ENF_ACTION_NUMBER":"918004","ENF_ACTION_ISSUE_DATE":"2013-06-04","ENF_ACTION_TYPE_ISSUED":"FORMAL ENFORCEMENT ACTION ISSUED"},{"WATER_SYSTEM_NUMBER":"CA4900716","WATER_SYSTEM_NAME":"CINNABAR ELEMENTARY SCHOOL","CITY":"PETALUMA","COUNTY":"SONOMA","ZIPCODE":"94952","CLASSIFICATION":"NON-TRANSIENT NON-COMMUNITY","POPULATION":"350","SERVICE_CONNECTIONS":"1","REGULATING_AGENCY":"DISTRICT 18 - SONOMA","VIOLATION_NUMBER":"718003","VIOLATION_TYPE_NAME":"MCL,  AVERAGE","ANALYTE_NAME":"ARSENIC","RESULT":".0113 MG/L","MCL":"NA","VIOL_BEGIN_DATE":"2013-01-01","VIOL_END_DATE":"2013-03-31","ENF_ACTION_NUMBER":"918006","ENF_ACTION_ISSUE_DATE":"2015-04-17","ENF_ACTION_TYPE_ISSUED":"RETURN TO COMPLIANCE"},{"WATER_SYSTEM_NUMBER":"CA4900716","WATER_SYSTEM_NAME":"CINNABAR ELEMENTARY SCHOOL","CITY":"PETALUMA","COUNTY":"SONOMA","ZIPCODE":"94952","CLASSIFICATION":"NON-TRANSIENT NON-COMMUNITY","POPULATION":"350","SERVICE_CONNECTIONS":"1","REGULATING_AGENCY":"DISTRICT 18 - SONOMA","VIOLATION_NUMBER":"718004","VIOLATION_TYPE_NAME":"MCL,  AVERAGE","ANALYTE_NAME":"ARSENIC","RESULT":"11.75 UG/L","MCL":"NA","VIOL_BEGIN_DATE":"2013-07-01","VIOL_END_DATE":"2013-09-30","ENF_ACTION_NUMBER":"918004","ENF_ACTION_ISSUE_DATE":"2013-06-04","ENF_ACTION_TYPE_ISSUED":"FORMAL ENFORCEMENT ACTION ISSUED"},{"WATER_SYSTEM_NUMBER":"CA4900716","WATER_SYSTEM_NAME":"CINNABAR ELEMENTARY SCHOOL","CITY":"PETALUMA","COUNTY":"SONOMA","ZIPCODE":"94952","CLASSIFICATION":"NON-TRANSIENT NON-COMMUNITY","POPULATION":"350","SERVICE_CONNECTIONS":"1","REGULATING_AGENCY":"DISTRICT 18 - SONOMA","VIOLATION_NUMBER":"718004","VIOLATION_TYPE_NAME":"MCL,  AVERAGE","ANALYTE_NAME":"ARSENIC","RESULT":"11.75 UG/L","MCL":"NA","VIOL_BEGIN_DATE":"2013-07-01","VIOL_END_DATE":"2013-09-30","ENF_ACTION_NUMBER":"918006","ENF_ACTION_ISSUE_DATE":"2015-04-17","ENF_ACTION_TYPE_ISSUED":"RETURN TO COMPLIANCE"},{"WATER_SYSTEM_NUMBER":"CA4900716","WATER_SYSTEM_NAME":"CINNABAR ELEMENTARY SCHOOL","CITY":"PETALUMA","COUNTY":"SONOMA","ZIPCODE":"94952","CLASSIFICATION":"NON-TRANSIENT NON-COMMUNITY","POPULATION":"350","SERVICE_CONNECTIONS":"1","REGULATING_AGENCY":"DISTRICT 18 - SONOMA","VIOLATION_NUMBER":"718005","VIOLATION_TYPE_NAME":"MCL,  AVERAGE","ANALYTE_NAME":"ARSENIC","RESULT":"12.3 UG/L","MCL":"NA","VIOL_BEGIN_DATE":"2013-10-01","VIOL_END_DATE":"2013-12-31","ENF_ACTION_NUMBER":"918004","ENF_ACTION_ISSUE_DATE":"2013-06-04","ENF_ACTION_TYPE_ISSUED":"FORMAL ENFORCEMENT ACTION ISSUED"},{"WATER_SYSTEM_NUMBER":"CA4900716","WATER_SYSTEM_NAME":"CINNABAR ELEMENTARY SCHOOL","CITY":"PETALUMA","COUNTY":"SONOMA","ZIPCODE":"94952","CLASSIFICATION":"NON-TRANSIENT NON-COMMUNITY","POPULATION":"350","SERVICE_CONNECTIONS":"1","REGULATING_AGENCY":"DISTRICT 18 - SONOMA","VIOLATION_NUMBER":"718005","VIOLATION_TYPE_NAME":"MCL,  AVERAGE","ANALYTE_NAME":"ARSENIC","RESULT":"12.3 UG/L","MCL":"NA","VIOL_BEGIN_DATE":"2013-10-01","VIOL_END_DATE":"2013-12-31","ENF_ACTION_NUMBER":"918006","ENF_ACTION_ISSUE_DATE":"2015-04-17","ENF_ACTION_TYPE_ISSUED":"RETURN TO COMPLIANCE"}]