[{"WATER_SYSTEM_NUMBER":"CA5410038","WATER_SYSTEM_NAME":"TERRA BELLA IRRIGATION DISTRICT - TBT","CITY":"TERRA BELLA","COUNTY":"TULARE","ZIPCODE":"93270","CLASSIFICATION":"COMMUNITY","POPULATION":"2340","SERVICE_CONNECTIONS":"979","REGULATING_AGENCY":"DISTRICT 12 - VISALIA","VIOLATION_NUMBER":"8912002","VIOLATION_TYPE_NAME":"MCL,  AVERAGE","ANALYTE_NAME":"TTHM","RESULT":"0.090 MG/L","MCL":"0.080 MG/L","VIOL_BEGIN_DATE":"2014-10-01","VIOL_END_DATE":"2014-12-31","ENF_ACTION_NUMBER":"9812005","ENF_ACTION_ISSUE_DATE":"2015-01-28","ENF_ACTION_TYPE_ISSUED":"FORMAL ENFORCEMENT ACTION ISSUED"},{"WATER_SYSTEM_NUMBER":"CA5410038","WATER_SYSTEM_NAME":"TERRA BELLA IRRIGATION DISTRICT - TBT","CITY":"TERRA BELLA","COUNTY":"TULARE","ZIPCODE":"93270","CLASSIFICATION":"COMMUNITY","POPULATION":"2340","SERVICE_CONNECTIONS":"979","REGULATING_AGENCY":"DISTRICT 12 - VISALIA","VIOLATION_NUMBER":"8912003","VIOLATION_TYPE_NAME":"MCL,  AVERAGE","ANALYTE_NAME":"TOTAL HALOACETIC ACIDS (HAA5)","RESULT":"0.069 MG/L","MCL":"0.060 MG/L","VIOL_BEGIN_DATE":"2014-10-01","VIOL_END_DATE":"2014-12-31","ENF_ACTION_NUMBER":"9812005","ENF_ACTION_ISSUE_DATE":"2015-01-28","ENF_ACTION_TYPE_ISSUED":"FORMAL ENFORCEMENT ACTION ISSUED"},{"WATER_SYSTEM_NUMBER":"CA5410038","WATER_SYSTEM_NAME":"TERRA BELLA IRRIGATION DISTRICT - TBT","CITY":"TERRA BELLA","COUNTY":"TULARE","ZIPCODE":"93270","CLASSIFICATION":"COMMUNITY","POPULATION":"2340","SERVICE_CONNECTIONS":"979","REGULATING_AGENCY":"DISTRICT 12 - VISALIA","VIOLATION_NUMBER":"8912007","VIOLATION_TYPE_NAME":"MCL, LRAA","ANALYTE_NAME":"TTHM","RESULT":"0.103 MG/L","MCL":"0.080 MG/L","VIOL_BEGIN_DATE":"2015-01-01","VIOL_END_DATE":"2015-03-31","ENF_ACTION_NUMBER":"9812006","ENF_ACTION_ISSUE_DATE":"2015-09-24","ENF_ACTION_TYPE_ISSUED":"FORMAL ENFORCEMENT ACTION ISSUED"},{"WATER_SYSTEM_NUMBER":"CA5410038","WATER_SYSTEM_NAME":"TERRA BELLA IRRIGATION DISTRICT - TBT","CITY":"TERRA BELLA","COUNTY":"TULARE","ZIPCODE":"93270","CLASSIFICATION":"COMMUNITY","POPULATION":"2340","SERVICE_CONNECTIONS":"979","REGULATING_AGENCY":"DISTRICT 12 - VISALIA","VIOLATION_NUMBER":"8912008","VIOLATION_TYPE_NAME":"MCL, LRAA","ANALYTE_NAME":"TOTAL HALOACETIC ACIDS (HAA5)","RESULT":"0.071 MG/L","MCL":"0.060 MG/L","VIOL_BEGIN_DATE":"2015-01-01","VIOL_END_DATE":"2015-03-31","ENF_ACTION_NUMBER":"9812005","ENF_ACTION_ISSUE_DATE":"2015-01-28","ENF_ACTION_TYPE_ISSUED":"FORMAL ENFORCEMENT ACTION ISSUED"},{"WATER_SYSTEM_NUMBER":"CA5410038","WATER_SYSTEM_NAME":"TERRA BELLA IRRIGATION DISTRICT - TBT","CITY":"TERRA BELLA","COUNTY":"TULARE","ZIPCODE":"93270","CLASSIFICATION":"COMMUNITY","POPULATION":"2340","SERVICE_CONNECTIONS":"979","REGULATING_AGENCY":"DISTRICT 12 - VISALIA","VIOLATION_NUMBER":"8912009","VIOLATION_TYPE_NAME":"MCL, LRAA","ANALYTE_NAME":"TTHM","RESULT":"0.144 MG/L","MCL":"0.080 MG/L","VIOL_BEGIN_DATE":"2015-04-01","VIOL_END_DATE":"2015-06-30","ENF_ACTION_NUMBER":"9812005","ENF_ACTION_ISSUE_DATE":"2015-01-28","ENF_ACTION_TYPE_ISSUED":"FORMAL ENFORCEMENT ACTION ISSUED"},{"WATER_SYSTEM_NUMBER":"CA5410038","WATER_SYSTEM_NAME":"TERRA BELLA IRRIGATION DISTRICT - TBT","CITY":"TERRA BELLA","COUNTY":"TULARE","ZIPCODE":"93270","CLASSIFICATION":"COMMUNITY","POPULATION":"2340","SERVICE_CONNECTIONS":"979","REGULATING_AGENCY":"DISTRICT 12 - VISALIA","VIOLATION_NUMBER":"8912010","VIOLATION_TYPE_NAME":"MCL, LRAA","ANALYTE_NAME":"TOTAL HALOACETIC ACIDS (HAA5)","RESULT":"0.112 MG/L","MCL":"0.060 MG/L","VIOL_BEGIN_DATE":"2015-04-01","VIOL_END_DATE":"2015-06-30","ENF_ACTION_NUMBER":"9812005","ENF_ACTION_ISSUE_DATE":"2015-01-28","ENF_ACTION_TYPE_ISSUED":"FORMAL ENFORCEMENT ACTION ISSUED"},{"WATER_SYSTEM_NUMBER":"CA5410038","WATER_SYSTEM_NAME":"TERRA BELLA IRRIGATION DISTRICT - TBT","CITY":"TERRA BELLA","COUNTY":"TULARE","ZIPCODE":"93270","CLASSIFICATION":"COMMUNITY","POPULATION":"2340","SERVICE_CONNECTIONS":"979","REGULATING_AGENCY":"DISTRICT 12 - VISALIA","VIOLATION_NUMBER":"8912011","VIOLATION_TYPE_NAME":"MCL, LRAA","ANALYTE_NAME":"TTHM","RESULT":"0.136 MG/L","MCL":"0.080 MG/L","VIOL_BEGIN_DATE":"2015-07-01","VIOL_END_DATE":"2015-09-30","ENF_ACTION_NUMBER":"9812005","ENF_ACTION_ISSUE_DATE":"2015-01-28","ENF_ACTION_TYPE_ISSUED":"FORMAL ENFORCEMENT ACTION ISSUED"},{"WATER_SYSTEM_NUMBER":"CA5410038","WATER_SYSTEM_NAME":"TERRA BELLA IRRIGATION DISTRICT - TBT","CITY":"TERRA BELLA","COUNTY":"TULARE","ZIPCODE":"93270","CLASSIFICATION":"COMMUNITY","POPULATION":"2340","SERVICE_CONNECTIONS":"979","REGULATING_AGENCY":"DISTRICT 12 - VISALIA","VIOLATION_NUMBER":"8912012","VIOLATION_TYPE_NAME":"MCL, LRAA","ANALYTE_NAME":"TOTAL HALOACETIC ACIDS (HAA5)","RESULT":"0.115 MG/L","MCL":"0.060 MG/L","VIOL_BEGIN_DATE":"2015-07-01","VIOL_END_DATE":"2015-09-30","ENF_ACTION_NUMBER":"9812005","ENF_ACTION_ISSUE_DATE":"2015-01-28","ENF_ACTION_TYPE_ISSUED":"FORMAL ENFORCEMENT ACTION ISSUED"},{"WATER_SYSTEM_NUMBER":"CA5410038","WATER_SYSTEM_NAME":"TERRA BELLA IRRIGATION DISTRICT - TBT","CITY":"TERRA BELLA","COUNTY":"TULARE","ZIPCODE":"93270","CLASSIFICATION":"COMMUNITY","POPULATION":"2340","SERVICE_CONNECTIONS":"979","REGULATING_AGENCY":"DISTRICT 12 - VISALIA","VIOLATION_NUMBER":"8912013","VIOLATION_TYPE_NAME":"MCL, LRAA","ANALYTE_NAME":"TTHM","RESULT":"0.150 MG/L","MCL":"0.080 MG/L","VIOL_BEGIN_DATE":"2015-10-01","VIOL_END_DATE":"2015-12-31","ENF_ACTION_NUMBER":"9812005","ENF_ACTION_ISSUE_DATE":"2015-01-28","ENF_ACTION_TYPE_ISSUED":"FORMAL ENFORCEMENT ACTION ISSUED"},{"WATER_SYSTEM_NUMBER":"CA5410038","WATER_SYSTEM_NAME":"TERRA BELLA IRRIGATION DISTRICT - TBT","CITY":"TERRA BELLA","COUNTY":"TULARE","ZIPCODE":"93270","CLASSIFICATION":"COMMUNITY","POPULATION":"2340","SERVICE_CONNECTIONS":"979","REGULATING_AGENCY":"DISTRICT 12 - VISALIA","VIOLATION_NUMBER":"8912014","VIOLATION_TYPE_NAME":"MCL, LRAA","ANALYTE_NAME":"TOTAL HALOACETIC ACIDS (HAA5)","RESULT":"0.131 MG/L","MCL":"0.060 MG/L","VIOL_BEGIN_DATE":"2015-10-01","VIOL_END_DATE":"2015-12-31","ENF_ACTION_NUMBER":"9812005","ENF_ACTION_ISSUE_DATE":"2015-01-28","ENF_ACTION_TYPE_ISSUED":"FORMAL ENFORCEMENT ACTION ISSUED"},{"WATER_SYSTEM_NUMBER":"CA5410038","WATER_SYSTEM_NAME":"TERRA BELLA IRRIGATION DISTRICT - TBT","CITY":"TERRA BELLA","COUNTY":"TULARE","ZIPCODE":"93270","CLASSIFICATION":"COMMUNITY","POPULATION":"2340","SERVICE_CONNECTIONS":"979","REGULATING_AGENCY":"DISTRICT 12 - VISALIA","VIOLATION_NUMBER":"8912015","VIOLATION_TYPE_NAME":"MCL, LRAA","ANALYTE_NAME":"TTHM","RESULT":"0.146 MG/L","MCL":"0.080 MG/L","VIOL_BEGIN_DATE":"2016-01-01","VIOL_END_DATE":"2016-03-31","ENF_ACTION_NUMBER":"9812005","ENF_ACTION_ISSUE_DATE":"2015-01-28","ENF_ACTION_TYPE_ISSUED":"FORMAL ENFORCEMENT ACTION ISSUED"},{"WATER_SYSTEM_NUMBER":"CA5410038","WATER_SYSTEM_NAME":"TERRA BELLA IRRIGATION DISTRICT - TBT","CITY":"TERRA BELLA","COUNTY":"TULARE","ZIPCODE":"93270","CLASSIFICATION":"COMMUNITY","POPULATION":"2340","SERVICE_CONNECTIONS":"979","REGULATING_AGENCY":"DISTRICT 12 - VISALIA","VIOLATION_NUMBER":"8912016","VIOLATION_TYPE_NAME":"MCL, LRAA","ANALYTE_NAME":"TOTAL HALOACETIC ACIDS (HAA5)","RESULT":"0.139 MG/L","MCL":"0.060 MG/L","VIOL_BEGIN_DATE":"2016-01-01","VIOL_END_DATE":"2016-03-31","ENF_ACTION_NUMBER":"9812005","ENF_ACTION_ISSUE_DATE":"2015-01-28","ENF_ACTION_TYPE_ISSUED":"FORMAL ENFORCEMENT ACTION ISSUED"},{"WATER_SYSTEM_NUMBER":"CA5410038","WATER_SYSTEM_NAME":"TERRA BELLA IRRIGATION DISTRICT - TBT","CITY":"TERRA BELLA","COUNTY":"TULARE","ZIPCODE":"93270","CLASSIFICATION":"COMMUNITY","POPULATION":"2340","SERVICE_CONNECTIONS":"979","REGULATING_AGENCY":"DISTRICT 12 - VISALIA","VIOLATION_NUMBER":"8912017","VIOLATION_TYPE_NAME":"MCL, LRAA","ANALYTE_NAME":"TTHM","RESULT":"0.127 MG/L","MCL":"0.080 MG/L","VIOL_BEGIN_DATE":"2016-04-01","VIOL_END_DATE":"2016-06-30","ENF_ACTION_NUMBER":"9812005","ENF_ACTION_ISSUE_DATE":"2015-01-28","ENF_ACTION_TYPE_ISSUED":"FORMAL ENFORCEMENT ACTION ISSUED"},{"WATER_SYSTEM_NUMBER":"CA5410038","WATER_SYSTEM_NAME":"TERRA BELLA IRRIGATION DISTRICT - TBT","CITY":"TERRA BELLA","COUNTY":"TULARE","ZIPCODE":"93270","CLASSIFICATION":"COMMUNITY","POPULATION":"2340","SERVICE_CONNECTIONS":"979","REGULATING_AGENCY":"DISTRICT 12 - VISALIA","VIOLATION_NUMBER":"8912018","VIOLATION_TYPE_NAME":"MCL, LRAA","ANALYTE_NAME":"TOTAL HALOACETIC ACIDS (HAA5)","RESULT":"0.127 MG/L","MCL":"0.060 MG/L","VIOL_BEGIN_DATE":"2016-04-01","VIOL_END_DATE":"2016-06-30","ENF_ACTION_NUMBER":"9812005","ENF_ACTION_ISSUE_DATE":"2015-01-28","ENF_ACTION_TYPE_ISSUED":"FORMAL ENFORCEMENT ACTION ISSUED"}]